LICENSE
MANIFEST.in
README.md
pyproject.toml
openequivariance/__init__.py
openequivariance.egg-info/PKG-INFO
openequivariance.egg-info/SOURCES.txt
openequivariance.egg-info/dependency_links.txt
openequivariance.egg-info/requires.txt
openequivariance.egg-info/top_level.txt
openequivariance/_torch/CUEConv.py
openequivariance/_torch/CUETensorProduct.py
openequivariance/_torch/E3NNConv.py
openequivariance/_torch/E3NNTensorProduct.py
openequivariance/_torch/FlashTPConv.py
openequivariance/_torch/NPDoubleBackwardMixin.py
openequivariance/_torch/TensorProduct.py
openequivariance/_torch/TensorProductConv.py
openequivariance/_torch/utils.py
openequivariance/_torch/extlib/.empty
openequivariance/_torch/extlib/__init__.py
openequivariance/_torch/symmetric_contraction/__init__.py
openequivariance/_torch/symmetric_contraction/symmetric_contraction.py
openequivariance/benchmark/ConvBenchmarkSuite.py
openequivariance/benchmark/TestBenchmarkSuite.py
openequivariance/benchmark/benchmark_utils.py
openequivariance/benchmark/correctness_utils.py
openequivariance/benchmark/logging_utils.py
openequivariance/benchmark/perf_metrics_utils.py
openequivariance/benchmark/problems.py
openequivariance/benchmark/random_buffer_utils.py
openequivariance/benchmark/tpp_creation_utils.py
openequivariance/benchmark/plotting/__init__.py
openequivariance/benchmark/plotting/plot_convolution.py
openequivariance/benchmark/plotting/plot_double_backward.py
openequivariance/benchmark/plotting/plot_roofline.py
openequivariance/benchmark/plotting/plot_uvu.py
openequivariance/benchmark/plotting/plot_uvw.py
openequivariance/benchmark/plotting/plotting_utils.py
openequivariance/core/ComputationSchedule.py
openequivariance/core/ConvolutionBase.py
openequivariance/core/LoopUnrollConv.py
openequivariance/core/LoopUnrollTP.py
openequivariance/core/TensorProductBase.py
openequivariance/core/e3nn_lite.py
openequivariance/core/utils.py
openequivariance/extension/convolution.hpp
openequivariance/extension/generic_module.cpp
openequivariance/extension/group_mm_cuda.hpp
openequivariance/extension/group_mm_hip.hpp
openequivariance/extension/libtorch_tp_jit.cpp
openequivariance/extension/tensorproducts.hpp
