Metadata-Version: 2.4
Name: openequivariance
Version: 0.5.1
Summary: A fast GPU JIT kernel generator for the Clebsch-Gordon Tensor Product
Author: Austin Glover, Vivek Bharadwaj, Aydin Buluc, James Demmel
License-Expression: BSD-3-Clause
Project-URL: homepage, https://passionlab.github.io/OpenEquivariance/
Project-URL: source, https://github.com/PASSIONLab/OpenEquivariance
Project-URL: issues, https://github.com/PASSIONLab/OpenEquivariance/issues
Classifier: Programming Language :: Python :: 3
Classifier: Programming Language :: Python :: 3.10
Classifier: Programming Language :: Python :: 3.11
Classifier: Programming Language :: Python :: 3.12
Classifier: Programming Language :: Python :: 3.13
Requires-Python: >=3.10
License-File: LICENSE
Requires-Dist: setuptools
Requires-Dist: ninja
Requires-Dist: jinja2
Requires-Dist: numpy
Provides-Extra: bench
Requires-Dist: matplotlib; extra == "bench"
Requires-Dist: tqdm; extra == "bench"
Requires-Dist: e3nn; extra == "bench"
Requires-Dist: cuequivariance; extra == "bench"
Requires-Dist: cuequivariance-torch; extra == "bench"
Requires-Dist: cuequivariance-ops-torch-cu12; extra == "bench"
Provides-Extra: dev
Requires-Dist: e3nn; extra == "dev"
Requires-Dist: pre-commit; extra == "dev"
Requires-Dist: ruff; extra == "dev"
Requires-Dist: pytest; extra == "dev"
Requires-Dist: pytest-check; extra == "dev"
Requires-Dist: pytest-subtests; extra == "dev"
Requires-Dist: torch_geometric; extra == "dev"
Requires-Dist: cmake; extra == "dev"
Provides-Extra: jax
Requires-Dist: nanobind; extra == "jax"
Requires-Dist: scikit-build-core; extra == "jax"
Requires-Dist: setuptools-scm; extra == "jax"
Dynamic: license-file
